Workbook

Sheet EDT-VALORES HH
A2: CALCULO ESFUERZO HH (HORAS HOMBRE) CAPITAL HUMANO | F2: COSTOS POR FASES | G2: JP | H2: AF | I2: DBA | J2: PG1 | K2: PG2 | L2: QA-TS | M2: COSTO FASE
F3: FASE ANALISIS PLANIFICACION | G3: =SUM(EDT!D4:D9)*'EDT-VALORES HH'!C6 -> 0 | H3: =SUM(EDT!E4:E9)*'EDT-VALORES HH'!C7 -> 0 | I3: =SUM(EDT!F4:F9)*'EDT-VALORES HH'!C8 -> 0 | J3: =SUM(EDT!G4:G9)*'EDT-VALORES HH'!C9 -> 0 | K3: =SUM(EDT!H4:H9)*'EDT-VALORES HH'!C10 -> 0 | L3: =SUM(EDT!I4:I9)*'EDT-VALORES HH'!C11 -> 0 | M3: =SUM(G3:L3) -> 0
F4: FASE DE DISEÑO- ESPECIF. | G4: =SUM(EDT!D11:D22)*'EDT-VALORES HH'!C6 -> 0 | H4: =SUM(EDT!E11:E22)*'EDT-VALORES HH'!C7 -> 0 | I4: =SUM(EDT!F11:F22)*'EDT-VALORES HH'!C8 -> 0 | J4: =SUM(EDT!G11:G22)*'EDT-VALORES HH'!C9 -> 0 | K4: =SUM(EDT!H11:H22)*'EDT-VALORES HH'!C10 -> 0 | L4: =SUM(EDT!I11:I22)*'EDT-VALORES HH'!C11 -> 0 | M4: =SUM(G4:L4) -> 0
A5: ACTOR | B5: N° HORAS | C5: VALOR HORA | D5: COSTO TOTAL HH | F5: FASE EJECUCION DESARROLLO | G5: =SUM(EDT!D23:D46)*'EDT-VALORES HH'!C6 -> 0 | H5: =SUM(EDT!E23:E46)*'EDT-VALORES HH'!C7 -> 0 | I5: =SUM(EDT!F23:F46)*'EDT-VALORES HH'!C8 -> 0 | J5: =SUM(EDT!G23:G46)*'EDT-VALORES HH'!C9 -> 0 | K5: =SUM(EDT!H23:H46)*'EDT-VALORES HH'!C10 -> 0 | L5: =SUM(EDT!I23:I46)*'EDT-VALORES HH'!C11 -> 0 | M5: =SUM(G5:L5) -> 0
A6: JP | B6: =EDT!D58 -> 0 | C6: 12778 | D6: =C6*B6 -> 0 | F6: FASE DE CIERRE | G6: =SUM(EDT!D48:D57)*'EDT-VALORES HH'!C6 -> 0 | H6: =SUM(EDT!E48:E57)*'EDT-VALORES HH'!C7 -> 0 | I6: =SUM(EDT!F48:F57)*'EDT-VALORES HH'!C8 -> 0 | J6: =SUM(EDT!G48:G57)*'EDT-VALORES HH'!C9 -> 0 | K6: =SUM(EDT!H48:H57)*'EDT-VALORES HH'!C10 -> 0 | L6: =SUM(EDT!I48:I57)*'EDT-VALORES HH'!C11 -> 0 | M6: =SUM(G6:L6) -> 0
A7: AF | B7: =EDT!E$58 -> 0 | C7: 10000 | D7: =C7*B7 -> 0 | F7: COSTO HH PROYECTO | M7: =SUM(M3:M6) -> 0
A8: DBA | B8: =EDT!F$58 -> 0 | C8: 6667 | D8: =C8*B8 -> 0
A9: PG1 | B9: =EDT!G$58 -> 0 | C9: 6667 | D9: =C9*B9 -> 0
A10: PG2 | B10: =EDT!H$58 -> 0 | C10: 6667 | D10: =C10*B10 -> 0
A11: QA-TS | B11: =EDT!I$58 -> 0 | C11: 6666.6667 | D11: =C11*B11 -> 0
B12: COSTO TOTAL HH | D12: =SUM(D6:D11) -> 0

Sheet EDT
B1: EDT | C1: T° x Tarea | D1: Roles
C2: Dias/horas | D2: JP | E2: AF | F2: DBA | G2: PG1 | H2: PG2 | I2: QA-TS | M2: DICCIONARIO EDT
A3: 1 | B3: Fase Análisis y Planificación | C3: Días | D3: Hrs. | M3: SIGLA ROL | N3: NOMBRE DEL ROL | O3: NOMBRE ACTOR
A4: 1.2 | B4: Kick Off | C4: 1 | M4: JP | N4: JEFE PROYECTO | O4: Roberto Olguin
A5: 1.3 | B5: Acta de Constitución de Proyecto | C5: 2 | M5: AF | N5: ANALISTA FUNCIONAL | O5: Mario Galarce
A6: 1.4 | B6: Aprobación del Acta | C6: 1 | M6: DBA | N6: DESARROLLADOR. BASE DATOS | O6: Alvaro Quiroz
A7: 1.5 | B7: Definición de Requerimientos Generales | C7: 3 | M7: PG1 | N7: PROGRAMADOR 1 | O7: Mario Galarce
A8: 1.6 | B8: Plan y riesgos | C8: 2 | M8: QA-TS | N8: QA- TESTING | O8: Alvaro Quiroz
A9: 1.7 | B9: Organización del Equipo | C9: 1
A10: 2 | B10: Fase Planificación y Diseño
A11: 2.1 | B11: Prototipo Figma v1 | C11: 4
A12: 2.2 | B12: Test de usabilidad & Prototipo v2 | C12: 3
A13: 2.3 | B13: Diseño de la solución / modelamientos | C13: 3
A14: 2.4 | B14: Modelo ER & diccionario de datos | C14: 3
A15: 2.5 | B15: Estrategia API & Swagger v1 | C15: 2
A16: 2.6 | B16: Repo/ramas & CI básica | C16: 1
A17: 2.7 | B17: Gantt | C17: 1
A18: 2.8 | B18: Diseño inicial de sistema (prototipo UX alto niv.) | C18: 2
A19: 2.9 | B19: Propuesta ERS (especificación requisitos SW) | C19: 2
A20: 2.10 | B20: Plan de proyecto (base calendaria) | C20: 2
A21: 2.11 | B21: Plan de riesgos (versión final) | C21: 2
A22: 2.12 | B22: Plan de gestión de calidad | C22: 1
A23: 3 | B23: Fase Ejecución
A24: 3.1 | B24: Implementación de la BD | L24: Todo esto es para solo 1 vista, tener en cuenta esto para las horas
B25: Implementación de la BD (ventana 09–21 oct) | C25: 1
A26: 3.1.1 | B26: Elegir y Levantar la base de datos para el sistema | C26: 2 | L26: no todos tienen horas en cada hito/artefacto
A27: 3.1.2 | B27: Diseño del MER | C27: 2 | L27: Llegar con todos los componentes y entregables para cargar horas
A28: 3.1.3 | B28: Crear Tablas Crud | C28: 1 | L28: Integracion y prueba cada fin de entregable
A29: 3.1.4 | B29: Crear usuarios | C29: 2
A30: 3.1.5 | B30: Insertar datos | C30: 1
A31: 3.2 | B31: Sistema Reserva
A32: 3.2.1 | B32: Motor de consulta de disponibilidad + prueba unitaria | C32: 3
A33: 3.2.2 | B33: Motor de reserva + Script + prueba unitaria | C33: 3
A34: 3.2.3 | B34: Formulario de pago Mercado Pago + Api + prueba unitaria | C34: 2
A35: 3.2.4 | B35: Vista pago realizado + Api ticket QR + prueba unitaria | C35: 2
A36: 3.2.5 | B36: Integración BD | C36: 1
A37: 3.2.6 | B37: Levantar página web | C37: 1
A38: 3.2.7 | B38: Integración del sistema | C38: 1
A39: 3.3 | B39: Aplicación de Administrador del Sistema | J39: actualizar
A40: 3.3.2 | B40: Vista principal administrador | C40: 1
A41: 3.3.3 | B41: Motor de inicio de sesión + PU | C41: 2
A42: 3.3.4 | B42: Integración BD | C42: 1
B43: Vista eliminación/modificación de usuarios + PU | C43: 1
A44: 3.3.5 | B44: Integración de la aplicación del Admin. | C44: 2
A45: 3.4 | B45: Servicios Adicionales
A46: 3.4.1 | B46: Inducción / capacitación a personal | C46: 2
A47: 4 | B47: Fase de Cierre
A48: 4.1 | B48: Pruebas de Integración por Plataforma | C48: 1
A49: 4.2 | B49: Migración del Sistema a Producción | C49: 2
A50: 4.3 | B50: Pruebas unitarias a cada componente | C50: 1
A51: 4.4 | B51: Pruebas Finales de cada componente | C51: 1
A52: 4.5 | B52: Marcha Blanca | C52: 1
A53: 4.6 | B53: Capacitación / Manuales de Usuario | C53: 2
A54: 4.7 | B54: Plan de Proyecto Final | C54: 1
A55: 4.8 | B55: Presentación Solemne | C55: 1 | L55: Hora hombre etc
A56: 4.9 | B56: Cierre del Proyecto | C56: 1
A57: 4.10 | B57: Carta de aceptación | C57: 1
B58: Días/Hrs. Totales | D58: =SUM(D48:D57,D24:D46,D11:D22,D4:D9) -> 0 | E58: =SUM(E48:E57,E23:E46,E11:E22,E4:E9) -> 0 | F58: =SUM(F48:F57,F23:F46,F11:F22,F4:F9) -> 0 | G58: =SUM(G48:G57,G23:G46,G11:G22,G4:G9) -> 0 | H58: =SUM(H48:H57,H23:H46,H11:H22,H4:H9) -> 0 | I58: =SUM(I48:I57,I23:I46,I11:I22,I4:I9) -> 0

Sheet GANTT
C1: MES 1 | AE1: MES 2 | BG1: MES 3 | CI1: MES 4 | DK1: MES 5
A2: N° | B2: SEMANAS | C2: SEMANA 1 | J2: SEMANA 2 | Q2: SEMANA 3 | X2: SEMANA 4 | AE2: SEMANA 5 | AL2: SEMANA 6 | AS2: SEMANA 7 | AZ2: SEMANA 8 | BG2: SEMANA 9 | BN2: SEMANA 10 | BU2: SEMANA 11 | CB2: SEMANA 12 | CI2: SEMANA 13 | CP2: SEMANA 14 | CW2: SEMANA 15 | DD2: SEMANA 16 | DK2: SEMANA 17 | DR2: SEMANA 18
B3: FASE ANALÍSIS Y PLANIFICACIÓN | C3: L | D3: M | E3: M | F3: J | G3: V | H3: S | I3: D | J3: L | K3: M | L3: M | M3: J | N3: V | O3: S | P3: D | Q3: L | R3: M | S3: M | T3: J | U3: V | V3: S | W3: D | X3: L | Y3: M | Z3: M | AA3: J | AB3: V | AC3: S | AD3: D | AE3: L | AF3: M | AG3: M | AH3: J | AI3: V | AJ3: S | AK3: D | AL3: L | AM3: M | AN3: M | AO3: J | AP3: V | AQ3: S | AR3: D | AS3: L | AT3: M | AU3: M | AV3: J | AW3: V | AZ3: L | BA3: M | BB3: M | BC3: J | BD3: V | BG3: L | BH3: M | BI3: M | BJ3: J | BK3: V | BN3: L | BO3: M | BP3: M | BQ3: J | BR3: V | BU3: L | BV3: M | BW3: M | BX3: J | BY3: V | CB3: L | CC3: M | CD3: M | CE3: J | CF3: V | CI3: L | CJ3: M | CK3: M | CL3: J | CM3: V | CP3: L | CQ3: M | CR3: M | CS3: J | CT3: V | CW3: L | CX3: M | CY3: M | CZ3: J | DA3: V | DD3: L | DE3: M | DF3: M | DG3: J | DH3: V | DK3: L | DL3: M | DM3: M | DN3: J | DO3: V | DR3: L | DS3: M | DT3: M | DU3: J | DV3: V
A4: 1 | B4: Kick Off
A5: 2 | B5: Acta de Constitución
A6: 3 | B6: Aprobación del Acta
A7: 4 | B7: Definición Requerimientos Generales
A8: 5 | B8: Plan y riesgos
A9: 6 | B9: Organización del Equipo
B10: FASE DE DISEÑO
A11: 7 | B11: Prototipo balsamic v1
A12: 8 | B12: Test de usabilidad & Prototipo v2
A13: 9 | B13: Diseño de la solución / modelamientos
A14: 10 | B14: Modelo ER & diccionario de datos | AH14: F | AI14: F
A15: 11 | B15: Estrategia API & Swagger v1
A16: 12 | B16: Repo/ramas & CI básica
A17: 13 | B17: Gantt
A18: 14 | B18: Diseño inicial de sistema
A19: 15 | B19: Propuesta ERS
A20: 16 | B20: Plan de proyecto
A21: 17 | B21: Plan de riesgos
A22: 18 | B22: Plan de gestión de calidad
B23: FASE DE EJECUCIÓN
B24: Implementación de la BD
B25: Elegir y Levantar la base de datos
B26: Diseño del MER
B27: Crear Tablas CRUD
B28: Crear usuarios
B29: Insertar datos
B30: Bloques funcionales
B31: API Core v1 (Auth, Clientes, Mascotas)
B32: Seguridad base
B33: Integración BD
B34: UI base & navegación
... B49: Despliegue demo
B50: Backups & DR | CF50: F
B51: Sistema Reserva
B52: Motor de consulta de disponibilidad
B53: Motor de reserva
B54: Vista pago realizado
B55: Integración BD
B56: Levantar página web | CF56: F
B57: Integración del sistema
B58: Aplicación de Administrador del Sistema
B59: Vista principal administrador
B60: Motor de inicio de sesión
B61: Integración BD (admin)
B62: FASE DE CIERRE
A63: 46 | B63: Documentación completa + video — Manual usuario/técnico, API, demo
A64: 47 | B64: Pre-entrega → Correcciones → Defensa/Entrega — Entrega final aprobada
C65: L | D65: M | E65: M | F65: J | G65: V | J65: L | K65: M | L65: M | M65: J | N65: V | Q65: L | R65: M | S65: M | T65: J | U65: V | X65: L | Y65: M | Z65: M | AA65: J | AB65: V | AE65: L | AF65: M | AG65: M | AH65: J | AI65: V | AL65: L | AM65: M | AN65: M | AO65: J | AP65: V | AS65: L | AT65: M | AU65: M | AV65: J | AW65: V | AZ65: L | BA65: M | BB65: M | BC65: J | BD65: V | BG65: L | BH65: M | BI65: M | BJ65: J | BK65: V | BN65: L | BO65: M | BP65: M | BQ65: J | BR65: V | BU65: L | BV65: M | BW65: M | BX65: J | BY65: V | CB65: L | CC65: M | CD65: M | CE65: J | CF65: V | CI65: L | CJ65: M | CK65: M | CL65: J | CM65: V | CP65: L | CQ65: M | CR65: M | CS65: J | CT65: V | CW65: L | CX65: M | CY65: M | CZ65: J | DA65: V | DD65: L | DE65: M | DF65: M | DG65: J | DH65: V | DK65: L | DL65: M | DM65: M | DN65: J | DO65: V | DR65: L | DS65: M | DT65: M | DU65: J | DV65: V
B67: SIMBOLOGIA
B68: CONTROL INTERNO | C68: CI
B69: REUNION CLIENTE | C69: RC
B70: HITO ENTREGA | C70: E
B71: DIA INACTIVO /FERIADO | C71: F
